MANIFEST.in
README.rst
setup.py
smallpress/__init__.py
smallpress/bootstrap.py
smallpress/helpers.py
smallpress/partials.py
smallpress/controllers/__init__.py
smallpress/controllers/root.py
smallpress/lib/__init__.py
smallpress/lib/forms.py
smallpress/lib/validators.py
smallpress/model/__init__.py
smallpress/model/models.py
smallpress/public/__init__.py
smallpress/public/__init__.pyc
smallpress/public/buttons/delete.png
smallpress/public/buttons/edit.png
smallpress/public/buttons/hide.png
smallpress/public/buttons/publish.png
smallpress/public/buttons/rmattachment.png
smallpress/public/ckeditor/ckeditor.js
smallpress/public/ckeditor/config.js
smallpress/public/ckeditor/contents.css
smallpress/public/ckeditor/images/spacer.gif
smallpress/public/ckeditor/lang/_languages.js
smallpress/public/ckeditor/lang/_translationstatus.txt
smallpress/public/ckeditor/lang/af.js
smallpress/public/ckeditor/lang/ar.js
smallpress/public/ckeditor/lang/bg.js
smallpress/public/ckeditor/lang/bn.js
smallpress/public/ckeditor/lang/bs.js
smallpress/public/ckeditor/lang/ca.js
smallpress/public/ckeditor/lang/cs.js
smallpress/public/ckeditor/lang/cy.js
smallpress/public/ckeditor/lang/da.js
smallpress/public/ckeditor/lang/de.js
smallpress/public/ckeditor/lang/el.js
smallpress/public/ckeditor/lang/en-au.js
smallpress/public/ckeditor/lang/en-ca.js
smallpress/public/ckeditor/lang/en-gb.js
smallpress/public/ckeditor/lang/en.js
smallpress/public/ckeditor/lang/eo.js
smallpress/public/ckeditor/lang/es.js
smallpress/public/ckeditor/lang/et.js
smallpress/public/ckeditor/lang/eu.js
smallpress/public/ckeditor/lang/fa.js
smallpress/public/ckeditor/lang/fi.js
smallpress/public/ckeditor/lang/fo.js
smallpress/public/ckeditor/lang/fr-ca.js
smallpress/public/ckeditor/lang/fr.js
smallpress/public/ckeditor/lang/gl.js
smallpress/public/ckeditor/lang/gu.js
smallpress/public/ckeditor/lang/he.js
smallpress/public/ckeditor/lang/hi.js
smallpress/public/ckeditor/lang/hr.js
smallpress/public/ckeditor/lang/hu.js
tgapp_smallpress.egg-info/PKG-INFO
tgapp_smallpress.egg-info/SOURCES.txt
tgapp_smallpress.egg-info/dependency_links.txt
tgapp_smallpress.egg-info/entry_points.txt
tgapp_smallpress.egg-info/not-zip-safe
tgapp_smallpress.egg-info/paster_plugins.txt
tgapp_smallpress.egg-info/requires.txt
tgapp_smallpress.egg-info/top_level.txt