Metadata-Version: 1.0
Name: tgapp-smallpress
Version: 0.6.0
Summary: Pluggable Minimalistic Blog for TurboGears2 with Attachments and Tags
Home-page: http://bitbucket.org/_amol_/tgapp-smallpress
Author: Alessandro Molina
Author-email: alessandro.molina@axant.it
License: UNKNOWN
Keywords: turbogears2.application
Platform: UNKNOWN
